setup.cfg
setup.py
src/mission_api/__init__.py
src/missioncloud_api.egg-info/PKG-INFO
src/missioncloud_api.egg-info/SOURCES.txt
src/missioncloud_api.egg-info/dependency_links.txt
src/missioncloud_api.egg-info/top_level.txt